__init__.py
api/__init__.py
api/atera.py
diffuse/__init__.py
gpt/__init__.py
harvest/__init__.py
utils/__init__.py
hawkscraper-0.0.1.dist-info/LICENSE
hawkscraper-0.0.1.dist-info/METADATA
hawkscraper-0.0.1.dist-info/WHEEL
hawkscraper-0.0.1.dist-info/top_level.txt
hawkscraper-0.0.1.dist-info/RECORD
