Metadata-Version: 2.1
Name: hawkscraper
Version: 0.0.1
Summary: An interface for routing/chaining API requests to various endpoints asynchronously and parsing/formatting the output.
Author-email: song-dog <coyote@coyote-ltd.com>
License: MIT License
Project-URL: Homepage, https://github.com/song-dog/hawkscraper
Project-URL: Bug Tracker, https://github.com/song-dog/hawkscraper/issues
Keywords: ai,gpt,api,scraping,convert,conversion,format,formatting
Classifier: Programming Language :: Python :: 3
Classifier: License :: OSI Approved :: MIT License
Classifier: Operating System :: OS Independent
Requires-Python: >=3.9
License-File: LICENSE
